pyebsdindex/__init__.py
pyebsdindex/_ebsd_index_parallel.py
pyebsdindex/_ebsd_index_single.py
pyebsdindex/band_detect.py
pyebsdindex/crystal_sym.py
pyebsdindex/crystallometry.py
pyebsdindex/ebsd_index.py
pyebsdindex/ebsd_pattern.py
pyebsdindex/ebsdfile.py
pyebsdindex/misorientation.py
pyebsdindex/nlpar.py
pyebsdindex/nlpar_cpu.py
pyebsdindex/pairlib.py
pyebsdindex/pcopt.py
pyebsdindex/radon_fast.py
pyebsdindex/rotations.py
pyebsdindex/rotlib.py
pyebsdindex/tripletvote.py
pyebsdindex/EBSDImage/IPFcolor.py
pyebsdindex/EBSDImage/OpenSans-Bold.ttf
pyebsdindex/EBSDImage/OpenSans-SemiBold.ttf
pyebsdindex/EBSDImage/__init__.py
pyebsdindex/EBSDImage/micronbar.py
pyebsdindex/EBSDImage/scalarimage.py
pyebsdindex/opencl/__init__.py
pyebsdindex/opencl/band_detect_cl.py
pyebsdindex/opencl/clkernels.cl
pyebsdindex/opencl/clnlpar.cl
pyebsdindex/opencl/nlpar_cl.py
pyebsdindex/opencl/nlpar_clray.py
pyebsdindex/opencl/openclparam.py
pyebsdindex/opencl/radon_fast_cl.py
pyebsdindex/opencl/test.cl
pyebsdindex/tests/__init__.py
pyebsdindex/tests/conftest.py
pyebsdindex/tests/numbatest.py
pyebsdindex/tests/raytest.py
pyebsdindex/tests/rotlibunittest.py
pyebsdindex/tests/test_ebsd_index.py
pyebsdindex/tests/test_package.py
pyebsdindex/tests/test_pcopt.py
pyebsdindex/tests/test_tripletvote.py
pyebsdindex/tests/data/al_sim_20kv/al_sim_20kv.png
pyebsdindex/tests/data/al_sim_20kv/generate_al_sim_20kv.py
pyebsdindex-0.3.8.dist-info/licenses/License
pyebsdindex-0.3.8.dist-info/METADATA
pyebsdindex-0.3.8.dist-info/WHEEL
pyebsdindex-0.3.8.dist-info/top_level.txt
pyebsdindex-0.3.8.dist-info/zip-safe
pyebsdindex-0.3.8.dist-info/RECORD
